qfinlib/__init__.py
qfinlib/calibration/__init__.py
qfinlib/calibration/curve/__init__.py
qfinlib/calibration/curve/builder.py
qfinlib/calibration/curve/engine.py
qfinlib/calibration/curve/factory/__init__.py
qfinlib/calibration/curve/factory/discount.py
qfinlib/calibration/curve/factory/forward.py
qfinlib/calibration/curve/factory/inflation.py
qfinlib/calibration/curve/instrument/__init__.py
qfinlib/calibration/curve/instrument/base.py
qfinlib/calibration/curve/instrument/bond.py
qfinlib/calibration/curve/instrument/deposit.py
qfinlib/calibration/curve/instrument/fra.py
qfinlib/calibration/curve/instrument/future.py
qfinlib/calibration/curve/instrument/swap.py
qfinlib/calibration/curve/solver.py
qfinlib/calibration/vol/__init__.py
qfinlib/calibration/vol/sabr.py
qfinlib/core/__init__.py
qfinlib/core/math/ad/__init__.py
qfinlib/core/math/ad/dual.py
qfinlib/core/math/ad/tape.py
qfinlib/core/math/interpolation/__init__.py
qfinlib/core/math/interpolation/base.py
qfinlib/core/math/interpolation/cubic.py
qfinlib/core/math/interpolation/linear.py
qfinlib/core/math/interpolation/log_linear.py
qfinlib/core/math/interpolation/monotone.py
qfinlib/core/math/solver/__init__.py
qfinlib/core/math/solver/brent.py
qfinlib/core/math/solver/levenberg_marquardt.py
qfinlib/core/math/solver/newton.py
qfinlib/core/math/stats/__init__.py
qfinlib/core/math/stats/distributions.py
qfinlib/core/math/stats/normal.py
qfinlib/core/utils/db/__init__.py
qfinlib/core/utils/db/mongo.py
qfinlib/core/utils/io/__init__.py
qfinlib/core/utils/io/csv.py
qfinlib/core/utils/io/json.py
qfinlib/date/__init__.py
qfinlib/date/bdc.py
qfinlib/date/date.py
qfinlib/date/dcf.py
qfinlib/date/holiday.py
qfinlib/date/interval.py
qfinlib/date/roll.py
qfinlib/date/schedule.py
qfinlib/date/tenor.py
qfinlib/instruments/__init__.py
qfinlib/instruments/base.py
qfinlib/instruments/bond/__init__.py
qfinlib/instruments/bond/bond.py
qfinlib/instruments/bond/fixed.py
qfinlib/instruments/bond/floating.py
qfinlib-2025.1229.1200.dist-info/METADATA
qfinlib-2025.1229.1200.dist-info/WHEEL
qfinlib-2025.1229.1200.dist-info/RECORD
